LICENSE
MANIFEST.in
README.md
setup.py
snowtrace/__init__.py
snowtrace/etherscan.py
snowtrace/configs/__init__.py
snowtrace/enums/__init__.py
snowtrace/enums/actions_enum.py
snowtrace/enums/fields_enum.py
snowtrace/enums/modules_enum.py
snowtrace/enums/tags_enum.py
snowtrace/modules/__init__.py
snowtrace/modules/accounts.py
snowtrace/modules/blocks.py
snowtrace/modules/contracts.py
snowtrace/modules/gastracker.py
snowtrace/modules/pro.py
snowtrace/modules/proxy.py
snowtrace/modules/stats.py
snowtrace/modules/tokens.py
snowtrace/modules/transactions.py
snowtrace/utils/__init__.py
snowtrace/utils/conversions.py
snowtrace/utils/parsing.py
snowtrace_python.egg-info/PKG-INFO
snowtrace_python.egg-info/SOURCES.txt
snowtrace_python.egg-info/dependency_links.txt
snowtrace_python.egg-info/not-zip-safe
snowtrace_python.egg-info/requires.txt
snowtrace_python.egg-info/top_level.txt
test/test_modules.py