Metadata-Version: 2.1
Name: snowtrace-python
Version: 2.1.0
Summary: A minimal, yet complete, python API for snowtrace.io.
Home-page: https://github.com/EmperorMew/snowtrace-python
Author: snowcone
Author-email: info@snowcones.io
License: MIT
Platform: UNKNOWN
License-File: LICENSE
